puncturedfem/__init__.py
puncturedfem/locfun/__init__.py
puncturedfem/locfun/antilap.py
puncturedfem/locfun/edge_space.py
puncturedfem/locfun/fft_deriv.py
puncturedfem/locfun/inner_prod.py
puncturedfem/locfun/local_harmonic.py
puncturedfem/locfun/local_poisson.py
puncturedfem/locfun/local_polynomial.py
puncturedfem/locfun/local_space.py
puncturedfem/locfun/locfun.py
puncturedfem/locfun/nystrom.py
puncturedfem/locfun/poly/__init__.py
puncturedfem/locfun/poly/barycentric.py
puncturedfem/locfun/poly/integrate_poly.py
puncturedfem/locfun/poly/legendre.py
puncturedfem/locfun/poly/monomial.py
puncturedfem/locfun/poly/multi_index.py
puncturedfem/locfun/poly/piecewise_poly.py
puncturedfem/locfun/poly/poly.py
puncturedfem/locfun/poly/poly_eval.py
puncturedfem/locfun/poly/poly_exceptions.py
puncturedfem/locfun/trace.py
puncturedfem/mesh/__init__.py
puncturedfem/mesh/bounding_box.py
puncturedfem/mesh/cell.py
puncturedfem/mesh/closed_contour.py
puncturedfem/mesh/edge.py
puncturedfem/mesh/edgelib/bean.py
puncturedfem/mesh/edgelib/cartioid.py
puncturedfem/mesh/edgelib/circle.py
puncturedfem/mesh/edgelib/circular_arc.py
puncturedfem/mesh/edgelib/circular_arc_deg.py
puncturedfem/mesh/edgelib/ellipse.py
puncturedfem/mesh/edgelib/line.py
puncturedfem/mesh/edgelib/sine_wave.py
puncturedfem/mesh/edgelib/spline.py
puncturedfem/mesh/edgelib/teardrop.py
puncturedfem/mesh/mesh_exceptions.py
puncturedfem/mesh/meshlib/__builder__.py
puncturedfem/mesh/meshlib/__init__.py
puncturedfem/mesh/meshlib/pacman.py
puncturedfem/mesh/meshlib/pacman_subdiv.py
puncturedfem/mesh/meshlib/pegboard.py
puncturedfem/mesh/meshlib/square_circular_hole.py
puncturedfem/mesh/planar_mesh.py
puncturedfem/mesh/quad.py
puncturedfem/mesh/split_edge.py
puncturedfem/mesh/transform.py
puncturedfem/mesh/vert.py
puncturedfem/plot/__init__.py
puncturedfem/plot/globfun_plot.py
puncturedfem/plot/locfun_plot.py
puncturedfem/plot/mesh_plot.py
puncturedfem/plot/plot_util.py
puncturedfem/plot/trace_plot.py
puncturedfem-0.5.0.dist-info/LICENSE
puncturedfem-0.5.0.dist-info/METADATA
puncturedfem-0.5.0.dist-info/WHEEL
puncturedfem-0.5.0.dist-info/RECORD
