Metadata-Version: 2.1
Name: puncturedfem
Version: 0.5.0
Summary: A finite element method on meshes with curvilinear and multiply connected cells.
License: GNU General Public License v3.0
Author: Sam Reynolds
Author-email: sreyn@proton.me
Requires-Python: >=3.9,<4.0
Classifier: License :: Other/Proprietary License
Classifier: Programming Language :: Python :: 3
Classifier: Programming Language :: Python :: 3.9
Classifier: Programming Language :: Python :: 3.10
Classifier: Programming Language :: Python :: 3.11
Classifier: Programming Language :: Python :: 3.12
Requires-Dist: Deprecated (>=1.2.14,<2.0.0)
Requires-Dist: matplotlib (>=3.8.0,<4.0.0)
Requires-Dist: numba (>=0.59.1,<0.60.0)
Requires-Dist: numpy (>=1.26.0,<2.0.0)
Requires-Dist: scipy (>=1.12.0,<2.0.0)
Requires-Dist: tqdm (>=4.66.1,<5.0.0)
